a_simple_llm_kit/__init__.py
a_simple_llm_kit/_version.py
a_simple_llm_kit/defaults.py
a_simple_llm_kit/adapters/__init__.py
a_simple_llm_kit/adapters/caching_chat_adapter.py
a_simple_llm_kit/core/__init__.py
a_simple_llm_kit/core/_string_utils.py
a_simple_llm_kit/core/circuit_breaker.py
a_simple_llm_kit/core/config.py
a_simple_llm_kit/core/context.py
a_simple_llm_kit/core/image_utils.py
a_simple_llm_kit/core/implementations.py
a_simple_llm_kit/core/logging.py
a_simple_llm_kit/core/metrics_wrappers.py
a_simple_llm_kit/core/model_interfaces.py
a_simple_llm_kit/core/opentelemetry_integration.py
a_simple_llm_kit/core/output_processors.py
a_simple_llm_kit/core/pipeline.py
a_simple_llm_kit/core/program_registry.py
a_simple_llm_kit/core/protocols.py
a_simple_llm_kit/core/providers.py
a_simple_llm_kit/core/storage.py
a_simple_llm_kit/core/types.py
a_simple_llm_kit/core/utils.py
a_simple_llm_kit/models/__init__.py
a_simple_llm_kit/models/manager.py
a_simple_llm_kit/models/predictor.py
a_simple_llm_kit/models/program_manager.py
a_simple_llm_kit/models/signatures.py
a_simple_llm_kit-0.4.1.dist-info/licenses/LICENSE
a_simple_llm_kit-0.4.1.dist-info/METADATA
a_simple_llm_kit-0.4.1.dist-info/WHEEL
a_simple_llm_kit-0.4.1.dist-info/top_level.txt
a_simple_llm_kit-0.4.1.dist-info/RECORD
