Metadata-Version: 2.4
Name: a-simple-llm-kit
Version: 0.4.1
Summary: A lightweight, extensible server for working with large language models, focused on pipeline processing and multi-modal capabilities. Built with FastAPI and DSPy.
Author-email: Charles Feinn <charles@appsimple.io>
License-Expression: MIT
Project-URL: Homepage, https://github.com/chuckfinca/a-simple-llm-kit
Classifier: Development Status :: 3 - Alpha
Classifier: Intended Audience :: Developers
Classifier: Programming Language :: Python :: 3.10
Requires-Python: >=3.10
License-File: LICENSE
Requires-Dist: fastapi[all]>=0.68.0
Requires-Dist: pydantic>=2.0.0
Requires-Dist: pydantic-settings>=2.0.0
Requires-Dist: python-dotenv>=0.19.0
Requires-Dist: pyyaml>=6.0.0
Requires-Dist: dspy-ai>=2.0.0
Requires-Dist: pillow>=10.0.0
Requires-Dist: python-multipart>=0.0.5
Provides-Extra: opentelemetry
Requires-Dist: opentelemetry-api~=1.25.0; extra == "opentelemetry"
Requires-Dist: opentelemetry-sdk~=1.25.0; extra == "opentelemetry"
Requires-Dist: opentelemetry-exporter-otlp~=1.25.0; extra == "opentelemetry"
Requires-Dist: opentelemetry-exporter-prometheus~=0.46b0; extra == "opentelemetry"
Requires-Dist: opentelemetry-semantic-conventions~=0.46b0; extra == "opentelemetry"
Requires-Dist: prometheus-client>=0.17.0; extra == "opentelemetry"
Provides-Extra: dev
Requires-Dist: mypy>=1.9.0; extra == "dev"
Requires-Dist: pytest>=7.0.0; extra == "dev"
Requires-Dist: ruff>=0.4.0; extra == "dev"
Requires-Dist: httpx>=0.23.0; extra == "dev"
Requires-Dist: email-validator>=2.0.0; extra == "dev"
Requires-Dist: pillow-heif; extra == "dev"
Requires-Dist: modal; extra == "dev"
Requires-Dist: trio; extra == "dev"
Requires-Dist: pytest-anyio; extra == "dev"
Requires-Dist: a-simple-llm-kit[opentelemetry]; extra == "dev"
Dynamic: license-file
